README.rst
setup.py
dna/__init__.py
dna/dna.py
just4demo.egg-info/PKG-INFO
just4demo.egg-info/SOURCES.txt
just4demo.egg-info/dependency_links.txt
just4demo.egg-info/top_level.txt