Metadata-Version: 1.0
Name: just4demo
Version: 0.0.1
Summary: some shit
Home-page: https://github.com/bgse/hellostackoverflow
Author: Emma Watson
Author-email: anshulk.it@gmail.com
License: MIT
Keywords: example
Platform: UNKNOWN
